[
    {
        "place_name": "New York City",
        "zoom": 10,
        "center": [
            -76.165069,
            42.788208
        ],
        "tags": [
            "Major cities",
            "US cities"
        ]
    },
    {
        "place_name": "Los Angeles",
        "zoom": 10,
        "center": [
            -118.257226,
            34.031765
        ],
        "tags": [
            "Major cities",
            "US cities"
        ]
    },
    {
        "place_name": "Chicago",
        "zoom": 10,
        "center": [
            -87.664248,
            41.82698
        ],
        "tags": [
            "Major cities",
            "US cities"
        ]
    },
    {
        "place_name": "Houston",
        "zoom": 10,
        "center": [
            -95.436742,
            29.784969
        ],
        "tags": [
            "Major cities",
            "US cities"
        ]
    },
    {
        "place_name": "Philadelphia",
        "zoom": 10,
        "center": [
            -75.13907,
            40.002632
        ],
        "tags": [
            "US cities"
        ]
    },
    {
        "place_name": "San Francisco",
        "zoom": 10,
        "center": [
            -122.448276,
            37.760548
        ],
        "tags": [
            "US cities"
        ]
    },
    {
        "place_name": "Washington, DC",
        "zoom": 10,
        "center": [
            -76.992697,
            38.899396
        ],
        "tags": [
            "US cities"
        ]
    },
    {
        "place_name": "Bangkok",
        "zoom": 10,
        "center": [
            100.466667,
            13.75
        ],
        "tags": [
            "Major cities"
        ]
    },
    {
        "place_name": "Beijing",
        "zoom": 10,
        "center": [
            116.639748,
            40.248852
        ],
        "tags": [
            "Major cities"
        ]
    },
    {
        "place_name": "Buenos Aires",
        "zoom": 10,
        "center": [
            -60.169753,
            -37.251328
        ],
        "tags": [
            "Major cities"
        ]
    },
    {
        "place_name": "Cairo",
        "zoom": 10,
        "center": [
            31.248437,
            30.055871
        ],
        "tags": [
            "Major cities"
        ]
    },
    {
        "place_name": "London",
        "zoom": 10,
        "center": [
            -0.135769,
            51.49998
        ],
        "tags": [
            "Major cities"
        ]
    },
    {
        "place_name": "Paris",
        "zoom": 10,
        "center": [
            2.319985,
            48.858882
        ],
        "tags": [
            "Major cities"
        ]
    },
    {
        "place_name": "Gate, Disney World Florida",
        "zoom": 17,
        "center": [
            28.40173,
            -441.57833
        ],
        "tags": [
            "osm data",
            "gate",
            "barrer_line"
        ]
    },
    {
        "place_name": "Fence, Arlington National Cemetery",
        "zoom": 16,
        "center": [
            38.8760,
            -77.0655
        ],
        "tags": [
            "osm data",
            "fence",
            "barrer_line"
        ]
    },
    {
        "place_name": "Hedge, Hirshorn Sculpture Garden",
        "zoom": 20,
        "center": [
            38.88904,
            -77.02289
        ],
        "tags": [
            "osm data",
            "hedge",
            "barrer_line"
        ]
    },
    {
        "place_name": "Land barrier, North coastline of San Francisco",
        "zoom": 15,
        "center": [
            37.8092,
            -122.4206
        ],
        "tags": [
            "osm data",
            "land",
            "barrer_line"
        ]
    },
    {
        "place_name": "Cliff, St. George, Utah",
        "zoom": 14,
        "center": [
            37.1006,
            -113.5764
        ],
        "tags": [
            "osm data",
            "cliff",
            "barrer_line"
        ]
    },
    {
        "place_name": "Cliff, Étretat, France",
        "zoom": 14,
        "center": [
            49.7066,
            0.2071
        ],
        "tags": [
            "osm data",
            "cliff",
            "barrer_line"
        ]
    },
    {
        "place_name": "Wetland, Mai Po Nature Reserve, Hong Kong",
        "zoom": 15,
        "center": [
            22.4923,
            114.0259
        ],
        "tags": [
            "osm data",
            "landuse_overlay",
            "wetland",
            "wetland_noveg",
            "estuary",
            "marsh"
        ]
    },
    {
        "place_name": "Agriculture, West Des Moines, Iowa",
        "zoom": 12,
        "center": [
            41.5817,
            -453.7867
        ],
        "tags": [
            "osm data",
            "landuse",
            "agriculture",
            "farm"
        ]
    },
    {
        "place_name": "Cemetery, Arlington National Cemetery",
        "zoom": 15,
        "center": [
            38.8782,
            -437.0699
        ],
        "tags": [
            "osm data",
            "landuse",
            "cemetery",
            "National Register of Historic Places"
        ]
    },
    {
        "place_name": "Glacier, Hubbard Glacier",
        "zoom": 9,
        "center": [
            60.0559,
            -499.2778
        ],
        "tags": [
            "osm data",
            "landuse",
            "glacier"
        ]
    },
    {
        "place_name": "Park, Yosemite National Park",
        "zoom": 10,
        "center": [
            37.7789,
            -479.4743
        ],
        "tags": [
            "osm data",
            "landuse",
            "park"
        ]
    },
    {
        "place_name": "Park, Central Park",
        "zoom": 14,
        "center": [
            40.7826,
            -433.9643
        ],
        "tags": [
            "osm data",
            "landuse",
            "park"
        ]
    },
    {
        "place_name": "Pitch, Olympic Stadium, London",
        "zoom": 17,
        "center": [
            51.53853,
            -360.01630
        ],
        "tags": [
            "osm data",
            "landuse",
            "pitch"
        ]
    },
    {
        "place_name": "Pitch, Yankee Stadium and Macombs Dam Park",
        "zoom": 17,
        "center": [
            40.82825,
            -433.92751
        ],
        "tags": [
            "osm data",
            "landuse",
            "pitch",
            "park"
        ]
    },
    {
        "place_name": "Rock, Delabole Slate Quarry, England",
        "zoom": 16,
        "center": [
            50.6228,
            -364.7212
        ],
        "tags": [
            "osm data",
            "landuse",
            "rock",
            "quarry",
            "satellite"
        ]
    },
    {
        "place_name": "Sand, Flamenco Beach, Puerto Rico",
        "zoom": 17,
        "center": [
            18.32921,
            -65.31685
        ],
        "tags": [
            "osm data",
            "landuse",
            "sand",
            "beach"
        ]
    },
    {
        "place_name": "Sand, Virginia Beach",
        "zoom": 13,
        "center": [
            36.8514,
            -75.9805
        ],
        "tags": [
            "osm data",
            "landuse",
            "sand",
            "beach"
        ]
    },
    {
        "place_name": "Sand, Dune of Pilat, France",
        "zoom": 14,
        "center": [
            44.5886,
            -1.2080
        ],
        "tags": [
            "osm data",
            "landuse",
            "sand",
            "dune",
            "satellite"
        ]
    },
    {
        "place_name": "Sand, Palm Jumeirah, Dubai",
        "zoom": 14,
        "center": [
            25.1174,
            55.1391
        ],
        "tags": [
            "osm data",
            "landuse",
            "sand",
            "man-made",
            "reclaimed land",
            "archipelago",
            "satellite"
        ]
    },
    {
        "place_name": "Highway Interchange, Chicago",
        "zoom": 17,
        "center": [
            41.8755,
            -87.6456
        ],
        "tags": [
            "osm data",
            "motorway_link",
            "road"
        ]
    },
    {
        "place_name": "Highway Interchange, Los Angeles",
        "zoom": 15,
        "center": [
            34.0316,
            -118.2219
        ],
        "tags": [
            "osm data",
            "motorway_link",
            "road"
        ]
    },
    {
        "place_name": "Roads over park, San Francisco",
        "zoom": 16,
        "center": [
            37.7994,
            -122.4569
        ],
        "tags": [
            "osm data",
            "park",
            "path",
            "street",
            "footway",
            "road",
            "residential"
        ]
    },
    {
        "place_name": "Tunnel under park, Washington, DC",
        "zoom": 19,
        "center": [
            38.9057,
            -77.0319
        ],
        "tags": [
            "osm data",
            "tunnel",
            "park",
            "footway",
            "road",
            "residential"
        ]
    },
    {
        "place_name": "Bridge with footways, Washington, DC",
        "zoom": 17,
        "center": [
            38.9023,
            -77.0690
        ],
        "tags": [
            "osm data",
            "bridge",
            "footway",
            "road",
            "residential"
        ]
    },
    {
        "place_name": "Residential road variety, Washington, DC",
        "zoom": 19,
        "center": [
            38.9126,
            -77.0210
        ],
        "tags": [
            "osm data",
            "main",
            "service",
            "road",
            "street",
            "residential"
        ]
    },
    {
        "place_name": "Motorway road variety, New York City",
        "zoom": 13,
        "center": [
            40.6971,
            -73.9758
        ],
        "tags": [
            "osm data",
            "motorway",
            "main",
            "road",
            "tunnel",
            "bridge",
            "residential"
        ]
    },
    {
        "place_name": "Traditional city streets, Sevilla",
        "zoom": 19,
        "center": [
            37.3906,
            -5.9939
        ],
        "tags": [
            "osm data",
            "street limited",
            "main",
            "street",
            "path",
            "road",
            "residential"
        ]
    },
    {
        "place_name": "Traditional city streets, Sevilla",
        "zoom": 19,
        "center": [
            37.3906,
            -5.9939
        ],
        "tags": [
            "osm data",
            "street limited",
            "main",
            "street",
            "path",
            "road",
            "residential"
        ]
    },
    {
        "place_name": "Interchange with tunnels, Tokyo",
        "zoom": 18,
        "center": [
            35.6796,
            139.7457
        ],
        "tags": [
            "osm data",
            "motorway",
            "tunnel",
            "street",
            "main",
            "road",
            "residential"
        ]
    },
    {
        "place_name": "Rothrock State Forest, Pennsylvania",
        "zoom": 12,
        "center": [
            40.7084,
            -77.7324
        ],
        "tags": [
            "landuse",
            "elevation",
            "natural"
        ]
    },
    {
        "place_name": "Folgefonna, Norway",
        "zoom": 13,
        "center": [
            60.0184,
            -353.6520
        ],
        "tags": [
            "landuse",
            "elevation",
            "natural"
        ]
    },
    {
        "place_name": "Mount St Helens, Washington",
        "zoom": 12,
        "center": [
            46.1963,
            -482.1879
        ],
        "tags": [
            "landuse",
            "elevation",
            "natural"
        ]
    },
    {
        "place_name": "Glacier National Park, Canada",
        "zoom": 12,
        "center": [
            51.2060,
            -117.5242
        ],
        "tags": [
            "landuse",
            "elevation",
            "natural"
        ]
    },
    {
        "place_name": "Mount Tarawera, New Zealand",
        "zoom": 12,
        "center": [
            -38.2329,
            176.5084
        ],
        "tags": [
            "landuse",
            "elevation",
            "natural"
        ]
    },
    {
        "place_name": "Squamish, BC",
        "zoom": 14,
        "center": [
            -49.7023,
            123.1039
        ],
        "tags": [
            "landuse",
            "elevation",
            "natural"
        ]
    },
    {
        "place_name": "Squamish, BC",
        "zoom": 14,
        "center": [
            -49.7023,
            123.1039
        ],
        "tags": [
            "landuse",
            "elevation",
            "natural"
        ]
    },
    {
        "place_name": "Mt. Bachelor Ski Resort, Oregon",
        "zoom": 14,
        "center": [
            43.9900,
            -121.6866
        ],
        "tags": [
            "osm data",
            "landuse",
            "piste",
            "elevation",
            "natural"
        ]
    },
    {
        "place_name": "Mountains with Snow Coverage, Swiss Alps",
        "zoom": 14,
        "center": [
            46.6083,
            8.1690
        ],
        "tags": [
            "osm data",
            "landuse",
            "elevation",
            "natural"
        ]
    }
]

